pygrabbit/__init__.py
pygrabbit/_compat.py
pygrabbit/_helpers.py
pygrabbit/parser.py
pygrabbit-0.3.0.dist-info/DESCRIPTION.rst
pygrabbit-0.3.0.dist-info/METADATA
pygrabbit-0.3.0.dist-info/metadata.json
pygrabbit-0.3.0.dist-info/RECORD
pygrabbit-0.3.0.dist-info/top_level.txt
pygrabbit-0.3.0.dist-info/WHEEL
